odoo/addons/product_supplierinfo_qty_multiplier/README.rst
odoo/addons/product_supplierinfo_qty_multiplier/__init__.py
odoo/addons/product_supplierinfo_qty_multiplier/__manifest__.py
odoo/addons/product_supplierinfo_qty_multiplier/i18n/fr.po
odoo/addons/product_supplierinfo_qty_multiplier/i18n/product_supplierinfo_qty_multiplier.pot
odoo/addons/product_supplierinfo_qty_multiplier/models/__init__.py
odoo/addons/product_supplierinfo_qty_multiplier/models/product_supplierinfo.py
odoo/addons/product_supplierinfo_qty_multiplier/models/purchase_order_line.py
odoo/addons/product_supplierinfo_qty_multiplier/readme/CONTRIBUTORS.rst
odoo/addons/product_supplierinfo_qty_multiplier/readme/DESCRIPTION.rst
odoo/addons/product_supplierinfo_qty_multiplier/readme/USAGE.rst
odoo/addons/product_supplierinfo_qty_multiplier/static/description/icon.png
odoo/addons/product_supplierinfo_qty_multiplier/static/description/index.html
odoo/addons/product_supplierinfo_qty_multiplier/tests/__init__.py
odoo/addons/product_supplierinfo_qty_multiplier/tests/test_purchase_order.py
odoo/addons/product_supplierinfo_qty_multiplier/views/product_supplierinfo_view.xml
odoo12_addon_product_supplierinfo_qty_multiplier-12.0.1.0.0.99.dev11.dist-info/METADATA
odoo12_addon_product_supplierinfo_qty_multiplier-12.0.1.0.0.99.dev11.dist-info/WHEEL
odoo12_addon_product_supplierinfo_qty_multiplier-12.0.1.0.0.99.dev11.dist-info/top_level.txt
odoo12_addon_product_supplierinfo_qty_multiplier-12.0.1.0.0.99.dev11.dist-info/RECORD
